aggie_unterprise/__init__.py
aggie_unterprise/aggie_report.py
aggie_unterprise/aggie_unterprise.py
aggie_unterprise-1.0.13.dist-info/licenses/LICENSE
aggie_unterprise-1.0.13.dist-info/METADATA
aggie_unterprise-1.0.13.dist-info/WHEEL
aggie_unterprise-1.0.13.dist-info/entry_points.txt
aggie_unterprise-1.0.13.dist-info/top_level.txt
aggie_unterprise-1.0.13.dist-info/RECORD
