Metadata-Version: 2.4
Name: aggie-unterprise
Version: 1.0.13
Summary: A Python package for extracting and processing grant data from AggieEnterprise spreadsheets.
Author-email: Dave Doty <doty@ucdavis.edu>
License: MIT
Project-URL: Homepage, https://github.com/dave-doty/aggie-unterprise
Project-URL: Issues, https://github.com/dave-doty/aggie-unterprise/issues
Project-URL: API, https://aggie-unterprise.readthedocs.io/
Requires-Python: >=3.7
License-File: LICENSE
Requires-Dist: openpyxl>=3.0.0
Requires-Dist: tabulate>=0.9.0
Provides-Extra: docs
Requires-Dist: mkdocs>=1.4.0; extra == "docs"
Requires-Dist: mkdocstrings[python]>=0.20.0; extra == "docs"
Requires-Dist: mkdocs-material>=9.1.0; extra == "docs"
Dynamic: license-file
